pyskyq/__init__.py
pyskyq/_h11_header_monkey_patch.py
pyskyq/_version.py
pyskyq/channel.py
pyskyq/constants.py
pyskyq/epg.py
pyskyq/programme.py
pyskyq/remote.py
pyskyq/status.py
pyskyq/utils.py
pyskyq/xmltvlisting.py
pyskyq/examples/cli_epg.py
pyskyq/examples/cli_remote.py
pyskyq/examples/cli_status.py
pyskyq-0.6.1.dist-info/METADATA
pyskyq-0.6.1.dist-info/RECORD
pyskyq-0.6.1.dist-info/WHEEL
pyskyq-0.6.1.dist-info/top_level.txt
