Metadata-Version: 2.1
Name: pyskyq
Version: 0.6.1
Summary: A python library to control a Sky Q Box
Home-page: https://gitlab.com/bradwood/pyskyq
Author: Bradley Wood
Author-email: pyskyq@bradleywood.com
License: mit
Platform: Mac
Platform: Linux
Classifier: Development Status :: 4 - Beta
Classifier: Programming Language :: Python
Classifier: Environment :: Console
Classifier: License :: OSI Approved :: MIT License
Classifier: Programming Language :: Python :: 3.7
Classifier: Topic :: Software Development :: Libraries
Classifier: Topic :: Utilities
Provides-Extra: aiosphinx
Provides-Extra: reno
Provides-Extra: dev
Requires-Dist: yarl
Requires-Dist: trio
Requires-Dist: asks
Requires-Dist: trio-websocket
Requires-Dist: python-dateutil
Requires-Dist: sortedcontainers
Requires-Dist: h11
Provides-Extra: aiosphinx
Requires-Dist: sphinxcontrib-asyncio; extra == 'aiosphinx'
Provides-Extra: dev
Requires-Dist: sphinx; extra == 'dev'
Requires-Dist: pytest; extra == 'dev'
Requires-Dist: pytest-cov; extra == 'dev'
Requires-Dist: pylint; extra == 'dev'
Requires-Dist: autopep8; extra == 'dev'
Requires-Dist: setuptools; extra == 'dev'
Requires-Dist: bumpversion; extra == 'dev'
Requires-Dist: pytest-mock; extra == 'dev'
Requires-Dist: twine; extra == 'dev'
Requires-Dist: docutils; extra == 'dev'
Requires-Dist: mypy; extra == 'dev'
Requires-Dist: rope; extra == 'dev'
Requires-Dist: reno[sphinx]; extra == 'dev'
Requires-Dist: asynctest; extra == 'dev'
Requires-Dist: pydocstyle; extra == 'dev'
Requires-Dist: python-dateutil; extra == 'dev'
Requires-Dist: sphinxcontrib-asyncio; extra == 'dev'
Requires-Dist: pytest-trio; extra == 'dev'
Provides-Extra: reno
Requires-Dist: reno[sphinx]; extra == 'reno'
